{
    "af-ZA": "Afrikaans (South Africa)",
    "id-ID": "Indonesian (Indonesia)",
    "ms-MY": "Malay (Malaysia)",
    "ca-ES": "Catalan (Spain)",
    "cs-CZ": "Czech (Czech Republic)",
    "da-DK": "Danish (Denmark)",
    "de-DE": "German (Germany)",
    "en-AU": "English (Australia)",
    "en-CA": "English (Canada)",
    "en-GB": "English (United Kingdom)",
    "en-IN": "English (India)",
    "en-IE": "English (Ireland)",
    "en-NZ": "English (New Zealand)",
    "en-PH": "English (Philippines)",
    "en-ZA": "English (South Africa)",
    "en-US": "English (United States)",
    "es-AR": "Spanish (Argentina)",
    "es-BO": "Spanish (Bolivia)",
    "es-CL": "Spanish (Chile)",
    "es-CO": "Spanish (Colombia)",
    "es-CR": "Spanish (Costa Rica)",
    "es-EC": "Spanish (Ecuador)",
    "es-SV": "Spanish (El Salvador)",
    "es-ES": "Spanish (Spain)",
    "es-US": "Spanish (United States)",
    "es-GT": "Spanish (Guatemala)",
    "es-HN": "Spanish (Honduras)",
    "es-MX": "Spanish (Mexico)",
    "es-NI": "Spanish (Nicaragua)",
    "es-PA": "Spanish (Panama)",
    "es-PY": "Spanish (Paraguay)",
    "es-PE": "Spanish (Peru)",
    "es-PR": "Spanish (Puerto Rico)",
    "es-DO": "Spanish (Dominican Republic)",
    "es-UY": "Spanish (Uruguay)",
    "es-VE": "Spanish (Venezuela)",
    "eu-ES": "Basque (Spain)",
    "fil-PH": "Filipino (Philippines)",
    "fr-CA": "French (Canada)",
    "fr-FR": "French (France)",
    "gl-ES": "Galician (Spain)",
    "hr-HR": "Croatian (Croatia)",
    "zu-ZA": "Zulu (South Africa)",
    "is-IS": "Icelandic (Iceland)",
    "it-IT": "Italian (Italy)",
    "lt-LT": "Lithuanian (Lithuania)",
    "hu-HU": "Hungarian (Hungary)",
    "nl-NL": "Dutch (Netherlands)",
    "no-NO": "Norwegian Bokmål (Norway)",
    "pl-PL": "Polish (Poland)",
    "pt-BR": "Portuguese (Brazil)",
    "pt-PT": "Portuguese (Portugal)",
    "ro-RO": "Romanian (Romania)",
    "sk-SK": "Slovak (Slovakia)",
    "sl-SI": "Slovenian (Slovenia)",
    "fi-FI": "Finnish (Finland)",
    "sv-SE": "Swedish (Sweden)",
    "vi-VN": "Vietnamese (Vietnam)",
    "tr-TR": "Turkish (Turkey)",
    "el-GR": "Greek (Greece)",
    "bg-BG": "Bulgarian (Bulgaria)",
    "ru-RU": "Russian (Russia)",
    "sr-RS": "Serbian (Serbia)",
    "uk-UA": "Ukrainian (Ukraine)",
    "iw-IL": "Hebrew",
    "ar-IL": "Arabic (Israel)",
    "ar-JO": "Arabic (Jordan)",
    "ar-AE": "Arabic (United Arab Emirates)",
    "ar-BH": "Arabic (Bahrain)",
    "ar-DZ": "Arabic (Algeria)",
    "ar-SA": "Arabic (Saudi Arabia)",
    "ar-IQ": "Arabic (Iraq)",
    "ar-KW": "Arabic (Kuwait)",
    "ar-MA": "Arabic (Morocco)",
    "ar-TN": "Arabic (Tunisia)",
    "ar-OM": "Arabic (Oman)",
    "ar-PS": "Arabic (State of Palestine)",
    "ar-QA": "Arabic (Qatar)",
    "ar-LB": "Arabic (Lebanon)",
    "ar-EG": "Arabic (Egypt)",
    "fa-IR": "Persian (Iran)",
    "hi-IN": "Hindi (India)",
    "th-TH": "Thai (Thailand)",
    "ko-KR": "Korean (South Korea)",
    "zh-TW": "Chinese Mandarin (Traditional, Taiwan)",
    "ja-JP": "Japanese (Japan)",
    "zh": "Chinese Mandarin (Simplified, China)"
}